g1asm/assembler.py
g1asm/binary_format.py
g1asm/data.py
g1asm/instructions.py
g1asm-0.3.1.dist-info/METADATA
g1asm-0.3.1.dist-info/WHEEL
g1asm-0.3.1.dist-info/entry_points.txt
g1asm-0.3.1.dist-info/RECORD
